<?xml version="1.0" encoding="ISO-8859-1"?>
<metadados xmlns:xsi="http://www.w3.org/2001/XMLSchema-instance" xsi:noNamespaceSchemaLocation="../.gradle/metadados.xsd">
  <table name="TGQREGFASES" sequenceType="A" sequenceField="IDREGFASES">
    <description>Histórico de Fases</description>
      <primaryKey>
          <field name="IDREGFASES"/>
      </primaryKey>
    <instances>
      <instance name="FasesNaoConforme">
        <description>Fases da Não Conforme</description>
        <relationShip>
          <relation entityName="CadastroFases" insert="N" update="N" relation="OneToOne" removeCascade="N">
            <fields>
              <field localName="FASESNCID" targetName="FASESNCID"/>
            </fields>
          </relation>
          <relation entityName="Usuario" insert="N" update="N" relation="OneToOne" removeCascade="N">
            <fields>
              <field localName="CODUSU" targetName="CODUSU"/>
            </fields>
          </relation>
        </relationShip>
      </instance>
    </instances>
    <fields>
      <field name="DATAFINAL" dataType="DATA_HORA" calculated="N" allowSearch="S" allowDefault="S" visibleOnSearch="S" isPresentation="N" order="6" nullable="S" visible="S" required="N">
        <description>Data Final</description>
        <properties>
          <prop name="UITabName">__main</prop>
          <prop name="visivel">N</prop>
        </properties>
      </field>
      <field name="RNCID" dataType="INTEIRO" calculated="N" allowSearch="S" allowDefault="S" visibleOnSearch="S" isPresentation="N" order="0" nullable="S" visible="S" required="N">
        <description>Id. Registro</description>
        <properties>
          <prop name="UITabName">__main</prop>
        </properties>
      </field>
      <field name="IDREGFASES" dataType="INTEIRO" calculated="N" allowSearch="S" allowDefault="S" visibleOnSearch="S" isPresentation="N" order="1" nullable="S" visible="S" required="N">
        <description>Id. Fases</description>
        <properties>
          <prop name="UITabName">__main</prop>
        </properties>
      </field>
      <field name="FASESNCID" dataType="INTEIRO" calculated="N" allowSearch="S" allowDefault="S" visibleOnSearch="S" isPresentation="N" order="2" nullable="S" visible="S" required="N">
        <description>Fase</description>
        <properties>
          <prop name="UITabName">__main</prop>
        </properties>
      </field>
      <field name="DATAFASE" dataType="DATA_HORA" calculated="N" allowSearch="S" allowDefault="S" visibleOnSearch="S" isPresentation="N" order="5" nullable="S" visible="S" required="N">
        <description>Data Fase</description>
        <expression>return getDateTime();</expression>
        <properties>
          <prop name="UITabName">__main</prop>
        </properties>
      </field>
      <field name="CODUSU" dataType="INTEIRO" calculated="N" allowSearch="S" allowDefault="S" visibleOnSearch="S" isPresentation="N" order="4" nullable="S" visible="S" required="N">
        <description>Usuário</description>
        <expression>return $ctx_usuario_logado;</expression>
        <properties>
          <prop name="UITabName">__main</prop>
        </properties>
      </field>
      <field name="PRAZODIAS" dataType="INTEIRO" calculated="N" allowSearch="S" allowDefault="S" visibleOnSearch="S" isPresentation="N" order="3" nullable="S" visible="S" required="N">
        <description>Prazo em dias</description>
        <properties>
          <prop name="UITabName">__main</prop>
          <prop name="visivel">N</prop>
        </properties>
      </field>
    </fields>
  </table>
</metadados>
